maisie/__init__.py
maisie/core.py
maisie/interface.py
maisie/logging.yaml
maisie/cli/__init__.py
maisie/cli/config.py
maisie/cli/models.py
maisie/cli/projects.py
maisie/cli/users.py
maisie/cli/workspaces.py
maisie/resources/__init__.py
maisie/resources/models.py
maisie/resources/projects.py
maisie/resources/users.py
maisie/resources/workspaces.py
maisie/utils/__init__.py
maisie/utils/auth.py
maisie/utils/errors.py
maisie/utils/git.py
maisie/utils/logging.py
maisie/utils/misc.py
utils/__init__.py
utils/git.py
Maisie-0.1.6.dist-info/METADATA
Maisie-0.1.6.dist-info/WHEEL
Maisie-0.1.6.dist-info/entry_points.txt
Maisie-0.1.6.dist-info/top_level.txt
Maisie-0.1.6.dist-info/RECORD
