Metadata-Version: 2.1
Name: Maisie
Version: 0.1.6
Summary: User-oriented system for painless managing, storing, sharing, organizing and deploying Machine Learning models.
Home-page: https://github.com/nokia-wroclaw/innovativeproject-ml-models-management
Author: Zofia Kochutek, Łukasz Kleczaj, Marek Kochanowski
Author-email: support@maisie.dev
License: MIT
Platform: UNKNOWN
Classifier: Development Status :: 4 - Beta
Classifier: Environment :: Console
Classifier: Intended Audience :: Developers
Classifier: License :: OSI Approved :: MIT License
Classifier: Natural Language :: English
Classifier: Operating System :: OS Independent
Classifier: Programming Language :: Python
Classifier: Programming Language :: Python :: 3 :: Only
Classifier: Programming Language :: Python :: 3.7
Classifier: Programming Language :: Python :: 3.8
Classifier: Topic :: Communications :: File Sharing
Classifier: Topic :: Scientific/Engineering
Classifier: Topic :: Scientific/Engineering :: Artificial Intelligence
Classifier: Topic :: Software Development :: Version Control :: Git
Classifier: Topic :: System :: Archiving :: Backup
Classifier: Typing :: Typed
Requires-Dist: Click (>=7.0)
Requires-Dist: gitpython (>=2.1.1)
Requires-Dist: requests (>=2.22.0)
Requires-Dist: coloredlogs (>=10.0)
Requires-Dist: pyyaml (>=5.1.1)
Requires-Dist: terminaltables (>=3.1.0)
Requires-Dist: ago (>=0.0.93)
Requires-Dist: python-dateutil (>=2.8.0)
